odoo9_addon_donation_bank_statement-9.0.1.0.0-py2.7-nspkg.pth
odoo_addons/donation_bank_statement/__openerp__.py
odoo_addons/donation_bank_statement/__init__.py
odoo_addons/donation_bank_statement/README.rst
odoo_addons/donation_bank_statement/security/ir.model.access.csv
odoo_addons/donation_bank_statement/models/__init__.py
odoo_addons/donation_bank_statement/models/company.py
odoo_addons/donation_bank_statement/models/donation.py
odoo_addons/donation_bank_statement/models/bank_statement.py
odoo_addons/donation_bank_statement/i18n/donation_bank_statement.pot
odoo_addons/donation_bank_statement/i18n/fr.po
odoo_addons/donation_bank_statement/views/bank_statement.xml
odoo_addons/donation_bank_statement/views/company.xml
odoo_addons/donation_bank_statement/views/donation.xml
odoo_addons/donation_bank_statement/demo/demo.xml
odoo_addons/donation_bank_statement/static/description/icon.png
odoo9_addon_donation_bank_statement-9.0.1.0.0.dist-info/top_level.txt
odoo9_addon_donation_bank_statement-9.0.1.0.0.dist-info/WHEEL
odoo9_addon_donation_bank_statement-9.0.1.0.0.dist-info/RECORD
odoo9_addon_donation_bank_statement-9.0.1.0.0.dist-info/metadata.json
odoo9_addon_donation_bank_statement-9.0.1.0.0.dist-info/DESCRIPTION.rst
odoo9_addon_donation_bank_statement-9.0.1.0.0.dist-info/METADATA
odoo9_addon_donation_bank_statement-9.0.1.0.0.dist-info/namespace_packages.txt
